ehdtd/__init__.py
ehdtd/binance.py
ehdtd/binanceus.py
ehdtd/bingx.py
ehdtd/bybit.py
ehdtd/ehdtd.py
ehdtd/ehdtd_common_functions.py
ehdtd/kucoin.py
ehdtd/okx.py
ehdtd-0.2.37.dist-info/METADATA
ehdtd-0.2.37.dist-info/WHEEL
ehdtd-0.2.37.dist-info/licenses/LICENSE
ehdtd-0.2.37.dist-info/RECORD
