Metadata-Version: 2.4
Name: ehdtd
Version: 0.2.37
Summary: Ehdtd - cryptoCurrency Exchange history data to database
License: MIT
License-File: LICENSE
Author: Ricardo Marcelo Alvarez
Author-email: rmalvarezkai@gmail.com
Requires-Python: >=3.13,<4.0
Classifier: License :: OSI Approved :: MIT License
Classifier: Programming Language :: Python :: 3
Classifier: Programming Language :: Python :: 3.13
Classifier: Programming Language :: Python :: 3.14
Requires-Dist: ccxt (>=4.5.17,<5.0.0)
Requires-Dist: ccxw (>=0.2.32,<0.3.0)
Requires-Dist: importlib (>=1.0.4,<2.0.0)
Requires-Dist: logging (>=0.4.9.6,<0.5.0.0)
Requires-Dist: pandas (>=2.3.3,<3.0.0)
Requires-Dist: psycopg2-binary (>=2.9.11,<3.0.0)
Requires-Dist: pymysql (>=1.1.2,<2.0.0)
Requires-Dist: schedule (>=1.2.2,<2.0.0)
Requires-Dist: sqlalchemy (>=2.0.44,<3.0.0)
Requires-Dist: thread6 (>=0.2.0,<0.3.0)
Project-URL: Homepage, https://github.com/rmalvarezkai/ehdtd
